perceptronPkg/__init__.py
perceptronPkg/perceptron.py
perceptron_pkg_anilans029-0.0.2.dist-info/LICENCE
perceptron_pkg_anilans029-0.0.2.dist-info/METADATA
perceptron_pkg_anilans029-0.0.2.dist-info/WHEEL
perceptron_pkg_anilans029-0.0.2.dist-info/top_level.txt
perceptron_pkg_anilans029-0.0.2.dist-info/RECORD
