Metadata-Version: 2.1
Name: perceptron-pkg-anilans029
Version: 0.0.2
Summary: A small package for perceptron
Home-page: https://github.com/anilans029/perceptron-pkg
Author: anilans029
Author-email: anilsai029@gmail.com
Project-URL: Bug Tracker, https://github.com/anilans029/perceptron-pkg/issues
Classifier: Programming Language :: Python :: 3
Classifier: License :: OSI Approved :: MIT License
Classifier: Operating System :: OS Independent
Requires-Python: >=3.6
License-File: LICENCE
Requires-Dist: numpy (==1.20.3)
Requires-Dist: joblib (==1.0.1)
Requires-Dist: pandas (==1.3.4)
Requires-Dist: matplotlib (==3.4.3)
